{
  "id": "k3-m1-de-kap1-2",
  "title": "Duits - Kapitel 1-2",
  "description": "Deutsch macht Spass Kapitel 1 + 2 Wortschatz",
  "language": { "from": "de", "to": "nl" },
  "tags": ["klas3", "module1", "vocabulary"],
  "source": "Deutsch macht Spass",
  "words": [
    { "id": "1.1-a", "term": "der Berg", "definition": "de berg", "extra": "der" },
    { "id": "1.1-b", "term": "die Berge", "definition": "de bergen", "extra": "die (pl)" },
    { "id": "1.2-a", "term": "der Wald", "definition": "het bos", "extra": "der" },
    { "id": "1.2-b", "term": "die Wälder", "definition": "de bossen", "extra": "die (pl)" },
    { "id": "1.3", "term": "der Himmel", "definition": "de lucht", "extra": "der" },
    { "id": "1.4", "term": "der See", "definition": "het meer", "extra": "der" },
    { "id": "1.5", "term": "der Nebel", "definition": "de mist", "extra": "der" },
    { "id": "1.6-a", "term": "der Ort", "definition": "de plaats", "extra": "der" },
    { "id": "1.6-b", "term": "die Orte", "definition": "de plaatsen", "extra": "die (pl)" },
    { "id": "1.7", "term": "der Regen", "definition": "de regen", "extra": "der" },
    { "id": "1.8-a", "term": "der Fluss", "definition": "de rivier", "extra": "der" },
    { "id": "1.8-b", "term": "die Flüsse", "definition": "de rivieren", "extra": "die (pl)" },
    { "id": "1.9", "term": "der Schnee", "definition": "de sneeuw", "extra": "der" },
    { "id": "1.10", "term": "der Verkehr", "definition": "het verkeer", "extra": "der" },
    { "id": "1.11", "term": "der Wind", "definition": "de wind", "extra": "der" },
    { "id": "1.12", "term": "die Insel", "definition": "het eiland", "extra": "die" },
    { "id": "1.13", "term": "die Natur", "definition": "de natuur", "extra": "die" },
    { "id": "1.14", "term": "die Umgebung", "definition": "de omgeving", "extra": "die" },
    { "id": "1.15", "term": "die Gegend", "definition": "de streek", "extra": "die" },
    { "id": "1.16", "term": "die Wolke", "definition": "de wolk", "extra": "die" },
    { "id": "1.17", "term": "die Sonne", "definition": "de zon", "extra": "die" },
    { "id": "1.18-a", "term": "das Tal", "definition": "het dal", "extra": "das" },
    { "id": "1.18-b", "term": "die Täler", "definition": "de dalen", "extra": "die (pl)" },
    { "id": "1.19-a", "term": "das Dorf", "definition": "het dorp", "extra": "das" },
    { "id": "1.19-b", "term": "die Dörfer", "definition": "de dorpen", "extra": "die (pl)" },
    { "id": "1.20", "term": "das Glatteis", "definition": "de ijzel", "extra": "das" },
    { "id": "1.21", "term": "das Gewitter", "definition": "het onweer", "extra": "das" },
    { "id": "1.22", "term": "das Wetter", "definition": "het weer", "extra": "das" },
    { "id": "1.23", "term": "das Meer", "definition": "de zee", "extra": "das" },
    { "id": "1.24", "term": "im Januar", "definition": "in januari", "extra": "" },
    { "id": "1.25", "term": "im Februar", "definition": "in februari", "extra": "" },
    { "id": "1.26", "term": "im März", "definition": "in maart", "extra": "" },
    { "id": "1.27", "term": "im April", "definition": "in april", "extra": "" },
    { "id": "1.28", "term": "im Mai", "definition": "in mei", "extra": "" },
    { "id": "1.29", "term": "im Juni", "definition": "in juni", "extra": "" },
    { "id": "1.30", "term": "im Juli", "definition": "in juli", "extra": "" },
    { "id": "1.31", "term": "im August", "definition": "in augustus", "extra": "" },
    { "id": "1.32", "term": "im September", "definition": "in september", "extra": "" },
    { "id": "1.33", "term": "im Oktober", "definition": "in oktober", "extra": "" },
    { "id": "1.34", "term": "im November", "definition": "in november", "extra": "" },
    { "id": "1.35", "term": "im Dezember", "definition": "in december", "extra": "" },
    { "id": "1.36", "term": "auf dem Land", "definition": "op het platteland", "extra": "" },
    { "id": "1.37", "term": "im Herbst", "definition": "in de herfst", "extra": "" },
    { "id": "1.38", "term": "im Frühling", "definition": "in de lente", "extra": "" },
    { "id": "1.39", "term": "im Winter", "definition": "in de winter", "extra": "" },
    { "id": "1.40", "term": "im Sommer", "definition": "in de zomer", "extra": "" },
    { "id": "1.41", "term": "im Norden", "definition": "in het noorden", "extra": "" },
    { "id": "1.42", "term": "im Osten", "definition": "in het oosten", "extra": "" },
    { "id": "1.43", "term": "im Westen", "definition": "in het westen", "extra": "" },
    { "id": "1.44", "term": "im Süden", "definition": "in het zuiden", "extra": "" },
    { "id": "1.45", "term": "es hagelt", "definition": "het hagelt", "extra": "v" },
    { "id": "1.46", "term": "es regnet", "definition": "het regent", "extra": "v" },
    { "id": "1.47", "term": "es friert", "definition": "het vriest", "extra": "v" },
    { "id": "1.48", "term": "es schneit", "definition": "het sneeuwt", "extra": "v" },
    { "id": "1.49", "term": "es ist windig", "definition": "het waait", "extra": "" },
    { "id": "1.50", "term": "die Sonne scheint", "definition": "de zon schijnt", "extra": "" },
    { "id": "1.51", "term": "es gibt", "definition": "er is, er zijn", "extra": "v" },
    { "id": "1.52", "term": "zelten", "definition": "kamperen", "extra": "v" },
    { "id": "1.53", "term": "wandern", "definition": "wandelen", "extra": "v" },
    { "id": "1.54", "term": "grillen", "definition": "barbecueën", "extra": "v" },
    { "id": "1.55", "term": "hektisch", "definition": "druk, hectisch", "extra": "adj" },
    { "id": "1.56", "term": "glatt", "definition": "glad", "extra": "adj" },
    { "id": "1.57", "term": "kalt – kälter", "definition": "koud", "extra": "adj" },
    { "id": "1.58", "term": "mehr", "definition": "meer", "extra": "" },
    { "id": "1.59", "term": "meistens", "definition": "meestal", "extra": "adv" },
    { "id": "1.60", "term": "weniger", "definition": "minder", "extra": "" },
    { "id": "1.61", "term": "ruhig", "definition": "rustig", "extra": "adj" },
    { "id": "1.62", "term": "steil", "definition": "steil", "extra": "adj" },
    { "id": "1.63", "term": "flach", "definition": "vlak", "extra": "adj" },
    { "id": "1.64", "term": "warm – wärmer", "definition": "warm", "extra": "adj" },
    { "id": "1.65", "term": "der Strand", "definition": "het strand", "extra": "der" },
    { "id": "1.66-a", "term": "die Stadt", "definition": "de stad", "extra": "die" },
    { "id": "1.66-b", "term": "die Städte", "definition": "de steden", "extra": "die (pl)" },
    { "id": "1.67-a", "term": "das Land", "definition": "het land", "extra": "das" },
    { "id": "1.67-b", "term": "die Länder", "definition": "de landen", "extra": "die (pl)" },
    { "id": "1.68", "term": "bleiben – geblieben", "definition": "blijven", "extra": "v" },
    { "id": "1.69", "term": "Fußball spielen", "definition": "voetballen", "extra": "v" },
    { "id": "1.70", "term": "sehen – gesehen", "definition": "zien", "extra": "v" },
    { "id": "1.71", "term": "abends", "definition": "'s avonds", "extra": "adv" },
    { "id": "1.72", "term": "nachmittags", "definition": "'s middags", "extra": "adv" },
    { "id": "1.73", "term": "heute Morgen", "definition": "vanmorgen", "extra": "" },
    { "id": "1.74", "term": "immer", "definition": "altijd", "extra": "adv" },
    { "id": "1.75", "term": "oft", "definition": "vaak", "extra": "adv" },
    { "id": "1.76", "term": "gut – besser", "definition": "goed – beter", "extra": "adj" },
    { "id": "1.77", "term": "heiß", "definition": "heet", "extra": "adj" },
    { "id": "1.78", "term": "langweilig", "definition": "saai", "extra": "adj" },
    { "id": "1.79", "term": "die Klimaveränderung", "definition": "de klimaatverandering", "extra": "die" },
    { "id": "1.80", "term": "die Auswirkung", "definition": "het effect", "extra": "die" },
    { "id": "1.81", "term": "gespannt sein", "definition": "benieuwd zijn", "extra": "adj" },
    { "id": "1.82", "term": "ganz", "definition": "heel", "extra": "adv" },
    { "id": "1.83", "term": "achten auf", "definition": "letten op", "extra": "v" },
    { "id": "1.84", "term": "unbedingt", "definition": "per se", "extra": "adv" },
    { "id": "1.85", "term": "die Nahrung", "definition": "de voeding", "extra": "die" },
    { "id": "1.86", "term": "wechselhaft", "definition": "onbestendig", "extra": "adj" },
    { "id": "1.87", "term": "derzeit", "definition": "momenteel", "extra": "adv" },
    { "id": "1.88", "term": "jedoch", "definition": "echter", "extra": "adv" },
    { "id": "1.89", "term": "kaum", "definition": "nauwelijks", "extra": "adv" },
    { "id": "1.90", "term": "außergewöhnlich", "definition": "buitengewoon", "extra": "adj" },
    { "id": "1.91", "term": "die Wettervorhersage", "definition": "de weersvoorspelling", "extra": "die" },
    { "id": "1.92", "term": "vorhersagen", "definition": "voorspellen", "extra": "v" },
    { "id": "1.93", "term": "einfach", "definition": "gewoon", "extra": "adv" },
    { "id": "1.94", "term": "die Nachbarn", "definition": "de buren", "extra": "die (pl)" },
    { "id": "1.95", "term": "verrückt", "definition": "gek", "extra": "adj" },
    { "id": "1.96", "term": "dennoch", "definition": "desondanks", "extra": "adv" },
    { "id": "1.97", "term": "irgendwann", "definition": "ergens/ooit", "extra": "adv" },
    { "id": "1.98", "term": "der öffentliche Verkehr", "definition": "het openbaar vervoer", "extra": "der" },
    { "id": "1.99", "term": "draußen", "definition": "buiten", "extra": "adv" },
    { "id": "1.100", "term": "außerdem", "definition": "bovendien", "extra": "adv" },
    { "id": "1.101", "term": "empfehlen", "definition": "aanraden", "extra": "v" },
    { "id": "1.102", "term": "mieten", "definition": "huren", "extra": "v" },
    { "id": "1.103", "term": "in der Nähe von", "definition": "in de buurt van", "extra": "" },
    { "id": "1.104", "term": "beeindruckend", "definition": "indrukwekkend", "extra": "adj" },
    { "id": "1.105", "term": "sich trauen", "definition": "durven", "extra": "v" },
    { "id": "1.106", "term": "das Erlebnis", "definition": "de ervaring", "extra": "das" },
    { "id": "1.107", "term": "der Aufenthalt", "definition": "het verblijf", "extra": "der" },
    { "id": "1.108", "term": "aufhören", "definition": "ophouden, stoppen", "extra": "v" },

    { "id": "2.1-a", "term": "der Arm", "definition": "de arm", "extra": "der" },
    { "id": "2.1-b", "term": "die Arme", "definition": "de armen", "extra": "die (pl)" },
    { "id": "2.2", "term": "der Bauch", "definition": "de buik", "extra": "der" },
    { "id": "2.3", "term": "der Arzt", "definition": "de arts, de dokter", "extra": "der" },
    { "id": "2.4", "term": "der Heuschnupfen", "definition": "de hooikoorts", "extra": "der" },
    { "id": "2.5", "term": "der Körper", "definition": "het lichaam", "extra": "der" },
    { "id": "2.6", "term": "der Magen", "definition": "de maag", "extra": "der" },
    { "id": "2.7", "term": "der Mund", "definition": "de mond", "extra": "der" },
    { "id": "2.8", "term": "der Hals", "definition": "de nek", "extra": "der" },
    { "id": "2.9", "term": "der Unfall", "definition": "het ongeluk", "extra": "der" },
    { "id": "2.10", "term": "der Rücken", "definition": "de rug", "extra": "der" },
    { "id": "2.11", "term": "der Muskelkater", "definition": "de spierpijn", "extra": "der" },
    { "id": "2.12-a", "term": "der Finger", "definition": "de vinger", "extra": "der" },
    { "id": "2.12-b", "term": "die Finger", "definition": "de vingers", "extra": "die (pl)" },
    { "id": "2.13-a", "term": "der Fuß", "definition": "de voet", "extra": "der" },
    { "id": "2.13-b", "term": "die Füße", "definition": "de voeten", "extra": "die (pl)" },
    { "id": "2.14", "term": "die Apotheke", "definition": "de apotheek", "extra": "die" },
    { "id": "2.15-a", "term": "die Hand", "definition": "de hand", "extra": "die" },
    { "id": "2.15-b", "term": "die Hände", "definition": "de handen", "extra": "die (pl)" },
    { "id": "2.16", "term": "die Gesundheit", "definition": "de gezondheid", "extra": "die" },
    { "id": "2.17", "term": "die Grippe", "definition": "de griep", "extra": "die" },
    { "id": "2.18", "term": "die Nase", "definition": "de neus", "extra": "die" },
    { "id": "2.19", "term": "die Erkältung", "definition": "de verkoudheid", "extra": "die" },
    { "id": "2.20", "term": "die Krankheit", "definition": "de ziekte", "extra": "die" },
    { "id": "2.21-a", "term": "das Bein", "definition": "het been", "extra": "das" },
    { "id": "2.21-b", "term": "die Beine", "definition": "de benen", "extra": "die (pl)" },
    { "id": "2.22", "term": "das Gesicht", "definition": "het gezicht", "extra": "das" },
    { "id": "2.23", "term": "das Fieber", "definition": "de koorts", "extra": "das" },
    { "id": "2.24-a", "term": "das Medikament", "definition": "het medicijn", "extra": "das" },
    { "id": "2.24-b", "term": "die Medikamente", "definition": "de medicijnen", "extra": "die (pl)" },
    { "id": "2.25-a", "term": "das Ohr", "definition": "het oor", "extra": "das" },
    { "id": "2.25-b", "term": "die Ohren", "definition": "de oren", "extra": "die (pl)" },
    { "id": "2.26", "term": "das Krankenhaus", "definition": "het ziekenhuis", "extra": "das" },
    { "id": "2.27", "term": "die Zahnschmerzen", "definition": "de kiespijn", "extra": "die (pl)" },
    { "id": "2.28", "term": "die Halsschmerzen", "definition": "de keelpijn", "extra": "die (pl)" },
    { "id": "2.29", "term": "die Schmerzen", "definition": "de pijn", "extra": "die (pl)" },
    { "id": "2.30", "term": "die Rückenschmerzen", "definition": "de rugpijn", "extra": "die (pl)" },
    { "id": "2.31", "term": "sich verletzen", "definition": "gewond raken", "extra": "v" },
    { "id": "2.32", "term": "zum Arzt gehen – gegangen", "definition": "naar de dokter gaan", "extra": "v" },
    { "id": "2.33", "term": "sich übergeben – übergeben", "definition": "overgeven", "extra": "v" },
    { "id": "2.34", "term": "wehtun – wehgetan", "definition": "pijn doen", "extra": "v" },
    { "id": "2.35", "term": "schlafen – geschlafen", "definition": "slapen", "extra": "v" },
    { "id": "2.36", "term": "sich schneiden – geschnitten", "definition": "zich snijden", "extra": "v" },
    { "id": "2.37", "term": "sich verbrennen – verbrannt", "definition": "zich branden", "extra": "v" },
    { "id": "2.38", "term": "sich fühlen", "definition": "zich voelen", "extra": "v" },
    { "id": "2.39", "term": "schwitzen", "definition": "zweten", "extra": "v" },
    { "id": "2.40", "term": "Gute Besserung!", "definition": "Beterschap!", "extra": "" },
    { "id": "2.41", "term": "froh", "definition": "blij", "extra": "adj" },
    { "id": "2.42", "term": "schwindlig", "definition": "duizelig", "extra": "adj" },
    { "id": "2.43", "term": "schlimm", "definition": "erg", "extra": "adj" },
    { "id": "2.44", "term": "verletzt", "definition": "gewond", "extra": "adj" },
    { "id": "2.45", "term": "gesund", "definition": "gezond", "extra": "adj" },
    { "id": "2.46", "term": "müde", "definition": "moe", "extra": "adj" },
    { "id": "2.47", "term": "ziemlich", "definition": "nogal, tamelijk", "extra": "adv" },
    { "id": "2.48", "term": "regelmäßig", "definition": "regelmatig", "extra": "adv" },
    { "id": "2.49", "term": "seit", "definition": "sinds", "extra": "" },
    { "id": "2.50", "term": "heute Abend", "definition": "vanavond", "extra": "" },
    { "id": "2.51", "term": "heute Nachmittag", "definition": "vanmiddag", "extra": "" },
    { "id": "2.52", "term": "erkältet", "definition": "verkouden", "extra": "adj" },
    { "id": "2.53", "term": "wieder", "definition": "weer", "extra": "adv" },
    { "id": "2.54", "term": "nervös", "definition": "zenuwachtig", "extra": "adj" },
    { "id": "2.55", "term": "krank", "definition": "ziek", "extra": "adj" },
    { "id": "2.56-a", "term": "der Zahn", "definition": "de tand", "extra": "der" },
    { "id": "2.56-b", "term": "die Zähne", "definition": "de tanden", "extra": "die (pl)" },
    { "id": "2.57-a", "term": "das Auge", "definition": "het oog", "extra": "das" },
    { "id": "2.57-b", "term": "die Augen", "definition": "de ogen", "extra": "die (pl)" },
    { "id": "2.58", "term": "besuchen", "definition": "bezoeken", "extra": "v" },
    { "id": "2.59", "term": "machen", "definition": "doen", "extra": "v" },
    { "id": "2.60", "term": "Rad fahren", "definition": "fietsen", "extra": "v" },
    { "id": "2.61", "term": "helfen – geholfen", "definition": "helpen", "extra": "v" },
    { "id": "2.62", "term": "können", "definition": "kunnen", "extra": "v" },
    { "id": "2.63", "term": "laufen – gelaufen", "definition": "lopen", "extra": "v" },
    { "id": "2.64", "term": "brauchen", "definition": "nodig hebben", "extra": "v" },
    { "id": "2.65", "term": "schreiben – geschrieben", "definition": "schrijven", "extra": "v" },
    { "id": "2.66", "term": "wünschen", "definition": "wensen", "extra": "v" },
    { "id": "2.67", "term": "gestern", "definition": "gisteren", "extra": "adv" },
    { "id": "2.68", "term": "vorige Woche", "definition": "vorige week", "extra": "" },
    { "id": "2.69", "term": "heiß", "definition": "heet", "extra": "adj" },
    { "id": "2.70", "term": "leider", "definition": "helaas", "extra": "adv" },
    { "id": "2.71", "term": "der Schritt", "definition": "de stap", "extra": "der" },
    { "id": "2.72", "term": "der Versuch", "definition": "de poging", "extra": "der" },
    { "id": "2.73", "term": "sich gewöhnen an", "definition": "wennen aan", "extra": "v" },
    { "id": "2.74", "term": "die Muskeln", "definition": "de spieren", "extra": "die (pl)" },
    { "id": "2.75", "term": "fast", "definition": "bijna", "extra": "adv" },
    { "id": "2.76", "term": "etwas schaffen", "definition": "voor elkaar krijgen", "extra": "v" },
    { "id": "2.77", "term": "gelingen", "definition": "lukken", "extra": "v" },
    { "id": "2.78", "term": "irgendwann", "definition": "ooit", "extra": "adv" },
    { "id": "2.79", "term": "die Leistung", "definition": "de prestatie", "extra": "die" },
    { "id": "2.80", "term": "das Ziel", "definition": "hier: de finish", "extra": "das" },
    { "id": "2.81", "term": "achten auf", "definition": "letten op", "extra": "v" },
    { "id": "2.82", "term": "die Strecke", "definition": "de route", "extra": "die" },
    { "id": "2.83", "term": "erschöpft sein", "definition": "uitgeput zijn", "extra": "adj" },
    { "id": "2.84", "term": "sich erholen", "definition": "uitrusten", "extra": "v" },
    { "id": "2.85", "term": "erklären", "definition": "uitleggen", "extra": "v" },
    { "id": "2.86", "term": "sofort", "definition": "meteen", "extra": "adv" },
    { "id": "2.87", "term": "das Gehirn", "definition": "de hersenen", "extra": "das" },
    { "id": "2.88", "term": "abspeichern", "definition": "opslaan", "extra": "v" },
    { "id": "2.89", "term": "bestimmt", "definition": "bepaald", "extra": "adj" },
    { "id": "2.90", "term": "schlecht gelaunt sein", "definition": "slecht gehumeurd zijn", "extra": "adj" },
    { "id": "2.91", "term": "während", "definition": "terwijl", "extra": "" },
    { "id": "2.92", "term": "verschwinden", "definition": "verdwijnen", "extra": "v" },
    { "id": "2.93", "term": "der Muskel", "definition": "de spier", "extra": "der" },
    { "id": "2.94", "term": "anschauen", "definition": "bekijken", "extra": "v" },
    { "id": "2.95", "term": "eine Menge", "definition": "veel", "extra": "" },
    { "id": "2.96", "term": "der Geruch", "definition": "de geur", "extra": "der" },
    { "id": "2.97", "term": "gar nichts", "definition": "helemaal niets", "extra": "" },
    { "id": "2.98", "term": "der Schnupfen", "definition": "de verkoudheid", "extra": "der" },
    { "id": "2.99", "term": "komisch", "definition": "raar, vreemd", "extra": "adj" }
  ]
}
